{
    "Data": {},
    "keyno": 0,
    "counter": 0,
    "userList": [],
    "GetIpIntel": true,
    "deepCheck": false,
    "AllowCheck": false,
    "LastCheck": 0,
    "ipinfo": {
        "status": true,
        "key": "2425356e4296a2"
    },
    "pckIO": [
        "1c7446-8nej52-d18m60-a27837",
        "6yv4z7-s375e0-532242-341970",
        "698152-971573-u77750-68z9i1"
    ],
    "ipqscr": [
        "n1pFxlB0ZHGSeQ3TfnDJ1PXEWrCTwnVe",
        "p9nUEH1U3X9uAP0ke0yREJqgUWsTnZQV",
        "kmH6yvIUjh1fvrsZbwFFw61gkoimVZZV"
    ],
    "FancyTxt": {
        "a": ["𝗔","𝘈","𝘼","Ａ","𝙰","𝐀","ᗩ","𝔸"],
        "b": ["𝗕","𝘉","𝘽","Ｂ","𝘽","𝐁","ᗷ","𝔹"],
        "c": ["𝗖","𝘊","𝘾","Ｃ","𝘾","𝐂","ᑕ","ℂ"],
        "d": ["𝗗","𝘋","𝘿","Ｄ","𝘿","𝐃","ᗪ","𝔻"],
        "e": ["𝗘","𝘌","𝙀","Ｅ","𝙴","𝐄","E","𝔼"],
        "f": ["𝗙","𝘍","𝙁","Ｆ","𝙵","𝐅","ᖴ","𝔽"],
        "g": ["𝗚","𝘎","𝙂","Ｇ","𝙂","𝐆","ᘜ","𝔾"],
        "h": ["𝗛","𝘏","𝙃","Ｈ","𝙷","𝐇","ᕼ","ℍ"],
        "i": ["𝗜","𝘐","𝙄","Ｉ","𝙸","𝐈","ᓮ","𝕀"],
        "j": ["𝗝","𝘑","𝙅","Ｊ","𝙹","𝐉","ᒍ","𝕁"],
        "k": ["𝗞","𝘒","𝙆","Ｋ","𝙺","𝐊","Ꮶ","𝕂"],
        "l": ["𝗟","𝘓","𝙇","Ｌ","𝙻","𝐋","ᒪ","𝕃"],
        "m": ["𝗠","𝘔","𝙈","Ｍ","𝙼","𝐌","ᙢ","𝕄"],
        "n": ["𝗡","𝘕","𝙉","Ｎ","𝙽","𝐍","ᑎ","ℕ"],
        "o": ["𝗢","𝘖","𝙊","Ｏ","𝙾","𝐎","O","𝕆"],
        "p": ["𝗣","𝘗","𝙋","Ｐ","𝙿","𝐏","ᑭ","ℙ"],
        "q": ["𝗤","𝘘","𝙌","Ｑ","𝚀","𝐐","ᑫ","ℚ"],
        "r": ["𝗥","𝘙","𝙍","Ｒ","𝚁","𝐑","ᖇ","ℝ"],
        "s": ["𝗦","𝘚","𝙎","Ｓ","𝚂","𝐒","ᔕ","𝕊"],
        "t": ["𝗧","𝘛","𝙏","Ｔ","𝚃","𝐓","T","𝕋"],
        "u": ["𝗨","𝘜","𝙐","Ｕ","𝚄","𝐔","ᑌ","𝕌"],
        "v": ["𝗩","𝘝","𝙑","Ｖ","𝚅","𝐕","ᐯ","𝕍"],
        "w": ["𝗪","𝘞","𝙒","Ｗ","𝚆","𝐖","ᗯ","𝕎"],
        "x": ["𝗫","𝘟","𝙓","Ｘ","𝚇","𝐗","᙭","𝕏"],
        "y": ["𝗬","𝘠","𝙔","Ｙ","𝚈","𝐘","Y","𝕐"],
        "z": ["𝗭","𝘡","𝙕","Ｚ","𝚉","𝐙","ᘔ","ℤ"]
    }
}
